qbox_types/__init__.py
qbox_types/data.py
qbox_types/trading.py
qbox_types-0.1.0.dist-info/METADATA
qbox_types-0.1.0.dist-info/WHEEL
qbox_types-0.1.0.dist-info/RECORD
