Metadata-Version: 2.4
Name: qbox-types
Version: 0.1.0
Summary: Core types, data structures, and enums for qbox
Author: QBox Team
License: MIT
Requires-Python: >=3.12
